winzy_time_in_words/__init__.py
winzy_time_in_words/time_in_words.py
winzy_time_in_words-0.0.1.dist-info/LICENSE
winzy_time_in_words-0.0.1.dist-info/METADATA
winzy_time_in_words-0.0.1.dist-info/WHEEL
winzy_time_in_words-0.0.1.dist-info/entry_points.txt
winzy_time_in_words-0.0.1.dist-info/top_level.txt
winzy_time_in_words-0.0.1.dist-info/RECORD
