Metadata-Version: 2.2
Name: winzy-time-in-words
Version: 0.0.1
Summary: Simple program to say time in words
Author: Sukhbinder Singh
License: Apache-2.0
Project-URL: Homepage, https://github.com/sukhbinder/winzy-time-in-words
Project-URL: Changelog, https://github.com/sukhbinder/winzy-time-in-words/releases
Project-URL: Issues, https://github.com/sukhbinder/winzy-time-in-words/issues
Project-URL: CI, https://github.com/sukhbinder/winzy-time-in-words/actions
Classifier: License :: OSI Approved :: Apache Software License
License-File: LICENSE
Requires-Dist: winzy
Provides-Extra: test
Requires-Dist: pytest; extra == "test"
